{"nodes": [{"id": "app_bank_callback_page", "label": "Bank Callback Page", "file_type": "code", "source_file": "app/bank-callback/page.tsx", "source_location": null, "source_url": null, "captured_at": null, "author": null, "contributor": null}, {"id": "concept_enable_banking_oauth", "label": "Enable Banking OAuth Integration", "file_type": "concept", "source_file": "app/bank-callback/page.tsx", "source_location": null, "source_url": null, "captured_at": null, "author": null, "contributor": null}], "edges": [{"source": "app_bank_callback_page", "target": "concept_enable_banking_oauth", "relation": "implements", "confidence": "INFERRED", "confidence_score": 0.85, "source_file": "app/bank-callback/page.tsx", "source_location": null, "weight": 0.8}], "hyperedges": []}